{"py/object": "rasa.core.featurizers.tracker_featurizers.MaxHistoryTrackerFeaturizer", "state_featurizer": {"py/object": "rasa.core.featurizers.single_state_featurizer.SingleStateFeaturizer", "_default_feature_states": {"intent": {"about_diseases": 0, "add_medication": 1, "affirm": 2, "back": 3, "bot_challenge": 4, "deny": 5, "goodbye": 6, "greet": 7, "list_medications": 8, "nlu_fallback": 9, "notify_medication_taken": 10, "out_of_scope": 11, "restart": 12, "session_start": 13}, "action_name": {"action_listen": 0, "action_restart": 1, "action_session_start": 2, "action_default_fallback": 3, "action_deactivate_loop": 4, "action_revert_fallback_events": 5, "action_default_ask_affirmation": 6, "action_default_ask_rephrase": 7, "action_two_stage_fallback": 8, "action_unlikely_intent": 9, "action_back": 10, "...": 11, "action_extract_slots": 12, "utter_add_medication_prompt": 13, "action_add_medication": 14, "utter_medication_added": 15, "utter_medication_add_failed": 16, "utter_medication_list": 17, "utter_no_medications_in_list": 18, "utter_your_medications_are": 19, "utter_specific_medication": 20, "utter_medication_details": 21, "utter_medication_not_found": 22, "utter_about_disease": 23, "utter_disease_description": 24, "utter_disease_info_unavailable": 25, "utter_medication_taken_confirmation": 26, "utter_medication_reminder_for_tomorrow": 27, "Utter_disease_description": 28, "Utter_medication_taken": 29, "Utter_medication_taken_confirmation": 30, "utter_cheer_up": 31, "utter_did_that_help": 32, "utter_goodbye": 33, "utter_greet": 34, "utter_happy": 35, "utter_iamabot": 36}, "entities": {"medication": 0}, "slots": {"medication_name_0": 0}, "active_loop": {}}, "action_texts": [], "entity_tag_specs": []}, "max_history": 5, "remove_duplicates": true}